[
  {
    "task": "volume_prediction",
    "predicted_volume": 0,
    "volume_level": "low",
    "timestamp": "2025-10-18T05:30:01.688197",
    "model_version": "1.0.0",
    "input_length": 30,
    "prediction_type": "volume",
    "model_info": {
      "name": "Kronos-Small",
      "version": "1.0.0",
      "description": "Simplified Kronos model for financial prediction",
      "parameters": 125000000,
      "architecture": "Transformer",
      "max_sequence_length": 512,
      "vocab_size": 10000,
      "num_layers": 12,
      "num_heads": 12,
      "hidden_size": 768,
      "intermediate_size": 3072
    }
  },
  {
    "task": "volume_prediction",
    "predicted_volume": 0,
    "volume_level": "low",
    "timestamp": "2025-10-18T05:30:06.952471",
    "model_version": "1.0.0",
    "input_length": 30,
    "prediction_type": "volume",
    "model_info": {
      "name": "Kronos-Small",
      "version": "1.0.0",
      "description": "Simplified Kronos model for financial prediction",
      "parameters": 125000000,
      "architecture": "Transformer",
      "max_sequence_length": 512,
      "vocab_size": 10000,
      "num_layers": 12,
      "num_heads": 12,
      "hidden_size": 768,
      "intermediate_size": 3072
    }
  },
  {
    "task": "volume_prediction",
    "predicted_volume": 0,
    "volume_level": "low",
    "timestamp": "2025-10-18T05:30:12.520840",
    "model_version": "1.0.0",
    "input_length": 30,
    "prediction_type": "volume",
    "model_info": {
      "name": "Kronos-Small",
      "version": "1.0.0",
      "description": "Simplified Kronos model for financial prediction",
      "parameters": 125000000,
      "architecture": "Transformer",
      "max_sequence_length": 512,
      "vocab_size": 10000,
      "num_layers": 12,
      "num_heads": 12,
      "hidden_size": 768,
      "intermediate_size": 3072
    }
  }
]